true_or_false/__init__.py
true_or_false/true_or_false.py
true_or_false-0.1.4.dist-info/LICENSE
true_or_false-0.1.4.dist-info/METADATA
true_or_false-0.1.4.dist-info/WHEEL
true_or_false-0.1.4.dist-info/RECORD
