Metadata-Version: 2.1
Name: true_or_false
Version: 0.1.4
Summary: A simple python module to determine whether an input is True or False.
Home-page: https://github.com/alpaalpa/true_or_false
License: MIT
Author: Albert Pang
Author-email: alpaalpa@mac.com
Requires-Python: >=3.6,<4.0
Classifier: License :: OSI Approved :: MIT License
Classifier: Programming Language :: Python :: 3
Classifier: Programming Language :: Python :: 3.6
Classifier: Programming Language :: Python :: 3.7
Classifier: Programming Language :: Python :: 3.8
Classifier: Programming Language :: Python :: 3.9
Classifier: Programming Language :: Python :: 3.10
Classifier: Programming Language :: Python :: 3.11
Classifier: Programming Language :: Python :: 3.12
